kitx/__about__.py
kitx/__init__.py
kitx/lib_async_multiprocess/__init__.py
kitx/lib_async_multiprocess/_core.py
kitx/lib_async_multiprocess/func.py
kitx/lib_async_multiprocess/tests/example.py
kitx/lib_fastapi/__init__.py
kitx/lib_file_storage/__init__.py
kitx/lib_file_storage/_cos.py
kitx/lib_file_storage/_minio.py
kitx/lib_file_storage/_oss.py
kitx/lib_file_storage/func.py
kitx/lib_file_storage/interface.py
kitx/lib_logging/README.md
kitx/lib_logging/__init__.py
kitx/lib_logging/core/__init__.py
kitx/lib_logging/core/_logger.py
kitx/lib_logging/core/_openobserve.py
kitx/lib_logging/core/_wraps.py
kitx/lib_utils/__init__.py
kitx/lib_utils/mem.py
kitx-1.0.15.dist-info/METADATA
kitx-1.0.15.dist-info/WHEEL
kitx-1.0.15.dist-info/licenses/LICENSE.txt
kitx-1.0.15.dist-info/RECORD
