Metadata-Version: 2.4
Name: kitx
Version: 1.0.15
Summary: kitx: A powerful toolbox; FamilyTools: kitx-snowflake (rs) build; 
Project-URL: Documentation, https://github.com/psb/kitx#readme
Project-URL: Issues, https://github.com/psb/kitx/issues
Project-URL: Source, https://github.com/psb/kitx
Author-email: kitx <carepsb@gmail.com>
License-Expression: MIT
License-File: LICENSE.txt
Keywords: FileStorage,logger,snowflake
Classifier: Development Status :: 4 - Beta
Classifier: Programming Language :: Python
Classifier: Programming Language :: Python :: 3.7
Classifier: Programming Language :: Python :: 3.8
Classifier: Programming Language :: Python :: 3.9
Classifier: Programming Language :: Python :: 3.10
Classifier: Programming Language :: Python :: 3.11
Classifier: Programming Language :: Python :: 3.12
Classifier: Programming Language :: Python :: 3.13
Classifier: Programming Language :: Python :: Implementation :: CPython
Classifier: Programming Language :: Python :: Implementation :: PyPy
Requires-Python: >=3.7
Requires-Dist: kitx-snowflake==1.1.1
Requires-Dist: loguru
Requires-Dist: pydantic
Requires-Dist: pydantic-settings
